Workbook

Sheet COVER&READ ME
A1: UBS/COMMERZBANK - M&A MODEL
A3: Transaction Overview
A4: Acquirer:UBS Group AG
A5: Target:Commerzbank AG
A6: Structure:100% Stock
A7: Announcement Date: May 2026
A9: Key assumptions(From assumptions tab)
A10: "CBK Price | B10: =ASSUMPTIONS!B12 -> 42.24
A11: Premium: | B11: =ASSUMPTIONS!B18 -> 0.24
A12: Purchase price | B12: =ASSUMPTIONS!B20/1000 -> 57.458227
A13: Exchange ratio | B13: =ASSUMPTIONS!B25 -> 1.1052458
A14: Synergies | B14: =ASSUMPTIONS!B30 -> 1500
A15: Restructuring | B15: =ASSUMPTIONS!B35 -> 2250
A17: KEY OUTPUTS
A18: Yr 1 Dilution | B18: ='M&A ENGINE'!B33 -> -0.20888722
A19: Yr 3 Dilution | B19: ='M&A ENGINE'!B34 -> -0.17029804
A20: Breakeven | B20: ='M&A ENGINE'!B35 -> >2028
A22: MODEL STRUCTURE
A23: Assumptions- FX, prices, premium,synergies
A24: UBS Standalone- UBS net income 2025-2028
A25: CBK Standalone- CBK net income (EUR/USD)
A26: CCA COMPS - DBK,BNP,ING,UCG Multiples
A27: Data sources- raw comp data
A28: M&A Engine- Accretion/dilution
A30: NOTES
A31: All figures in USD
A32: Tax rate:22% , Cost of debt:4.5%
A33: Synergies phased 60%/85%/100%

Sheet ASSUMPTIONS
A1: UBS/COMMERZBANK M&A TRANSACTION MODEL
A3: Global parameters &FX conversion
A4: EUR/USD Exchange rate | B4: 1.16
A5: NOTE: All figures in USD
A6: STANDALONE BASELINE DATA
A7: UBS Group AG (ACQUIRER)
A8: Current share price | B8: =47.39 -> 47.39
A9: Fully diluted shares outstanding | B9: 3185
A10: Implied standalone equity value | B10: =B8*B9 -> 150937.15
A11: COMMERZBANK AG (TARGET)
A12: Current share price | B12: 42.24
A13: Basic shares outstanding | B13: 1097
A14: Plus:Dilutive securities | B14: 29
A15: Fully diluted shares | B15: =B13+B14 -> 1126
A17: DEAL STRUCTURE & PURCHASE PRICE
A18: Assumed acquisition premium | B18: 0.24
A19: Implied offer price per share | B19: =B12*(1+B18) -> 52.3776
A20: Implied transaction equity value | B20: =B13*B19 -> 57458.227
A22: Offer structure
A23: %Stock consideration | B23: 1
A24: %Cash consideration | B24: 0
A25: Implied exchange ratio | B25: =B19/B8 -> 1.1052458
A26: New UBS shares issued | B26: =B20/B8 -> 1212.4547
A27: Proforma FD shares out | B27: =B9+B26 -> 4397.4547
A29: TRANSACTION SYNERGIES &TAX PARAMETERS
A30: Estimated pre-tax cost synergies | B30: 1500
A31: UBS corporate tax rate | B31: 0.22
A32: After-tax annual cost synergies | B32: =B30*(1-B31) -> 1170
A34: Reatructuring cost multiple | B34: 1.5
A35: Total restructuring cost | B35: =B30*B34 -> 2250
A36: %Phased year 1 | B36: 0.6
A37: %Phased year 2 | B37: 0.85
A38: %Phased year 3 | B38: 1

Sheet UBS STANDALONE
A1: UBS STANDALONE | B1: Net income($m)
A2: YEAR
A3: 2025 | B3: 7800
A4: 2026 | B4: 7200
A5: 2027 | B5: 7500
A6: 2028 | B6: 7800

Sheet CBK STANDALONE
A2: CBK STANDALONE | B2: NET INCOME ($M)
A3: YEAR
A4: 2025 | B4: 2753.84
A5: 2026 | B5: 2836
A6: 2027 | B6: 2922
A7: 2028 | B7: 3009

Sheet CCA COMPS
A1: COMPANY COMPARABLE ANALYSIS
A2: Company | B2: Ticker | C2: Market cap | D2: Net income | E2: P/E | F2: P/B
A3: Deutsche bank | B3: DBK | C3: ='DATA SOURCES'!B3*'DATA SOURCES'!E3 -> 85115.956 | D3: ='DATA SOURCES'!I3 -> 8281.24 | E3: =C3/D3 -> 10.278166 | F3: =C3/'DATA SOURCES'!N3 -> 1.0962578
A4: BNP Paribas | B4: BNP | C4: ='DATA SOURCES'!B4*'DATA SOURCES'!E4 -> 121210.82 | D4: ='DATA SOURCES'!I4 -> 14181 | E4: =C4/D4 -> 8.5474101 | F4: =C4/'DATA SOURCES'!N4 -> 0.83252004
A5: ING group | B5: INGA | C5: ='DATA SOURCES'!B5*'DATA SOURCES'!E5 -> 80825.343 | D5: ='DATA SOURCES'!I5 -> 7308 | E5: =C5/D5 -> 11.059844 | F5: =C5/'DATA SOURCES'!N5 -> 1.4020085
A6: UniCredit | B6: UCG | C6: ='DATA SOURCES'!B6*'DATA SOURCES'!E6 -> 124453.82 | D6: ='DATA SOURCES'!I6 -> 12785.52 | E6: =C6/D6 -> 9.7339662 | F6: =C6/'DATA SOURCES'!N6 -> 1.5844955
A8: STATISTICS
A9: Average | E9: =AVERAGE(E3:E6) -> 9.9048466 | F9: =AVERAGE(F3:F6) -> 1.2288205
A10: Median | E10: =MEDIAN(E3:E6) -> 10.006066 | F10: =MEDIAN(F3:F6) -> 1.2491332
A11: Low | E11: =MIN(E3:E6) -> 8.5474101 | F11: =MIN(F3:F6) -> 0.83252004
A12: High | E12: =MAX(E3:E6) -> 11.059844 | F12: =MAX(F3:F6) -> 1.5844955

Sheet DATA SOURCES
C1: (EURO)
B2: SHARES OUTSTANDING | C2: SHARE PRICE ( 31 DEC 2025) | E2: SHARE PRICE IN (USD) | G2: NET INCOME(EUROS) | I2: NET INCOME(USD) | K2: TOTAL SHAREHOLDERS EQUITY (EURO) | N2: TOTAL SHAREHOLDER EQUITY (USD)
A3: Deutsche bank | B3: 1902.9 | C3: 38.56 | E3: =C3*ASSUMPTIONS!B4 -> 44.7296 | G3: 7139 | I3: =G3*ASSUMPTIONS!B4 -> 8281.24 | K3: 66933 | N3: =K3*ASSUMPTIONS!B4 -> 77642.28
A4: BNP Paribas | B4: 1129.4 | C4: 92.52 | E4: =C4*ASSUMPTIONS!B4 -> 107.3232 | G4: 12225 | I4: =G4*ASSUMPTIONS!B4 -> 14181 | K4: 125513 | N4: =K4*ASSUMPTIONS!B4 -> 145595.08
A5: ING group | B5: 2902 | C5: 24.01 | E5: =C5*ASSUMPTIONS!B4 -> 27.8516 | G5: 6300 | I5: =G5*ASSUMPTIONS!B4 -> 7308 | K5: 49698 | N5: =K5*ASSUMPTIONS!B4 -> 57649.68
A6: UniCredit | B6: 1512.8 | C6: 70.92 | E6: =C6*ASSUMPTIONS!B4 -> 82.2672 | G6: 11022 | I6: =G6*ASSUMPTIONS!B4 -> 12785.52 | K6: 67711 | N6: =K6*ASSUMPTIONS!B4 -> 78544.76

Sheet M&A ENGINE
A1: ACCRETION/DILUTION ANALYSIS
A2: ($Millions )
A4: Assumptions | D4: Financing | F4: Projection period | G4: 2026 | H4: 2027 | I4: 2028
A5: Purchase price | B5: =ASSUMPTIONS!B20/1000 -> 57.458227 | D5: Shares issued | E5: =ASSUMPTIONS!B26 -> 1212.4547
A6: %Stock consideration | B6: =ASSUMPTIONS!B23 -> 1 | D6: New debt for restructuring | E6: =B8+50 -> 2300
A7: %Cash consideration | B7: =ASSUMPTIONS!B24 -> 0 | D7: Cost of debt | E7: 0.045
A8: Restructuring cost | B8: =ASSUMPTIONS!B35 -> 2250
A9: Cost to achieve multiple | B9: =ASSUMPTIONS!B34 -> 1.5
A10: Tax rate | B10: =ASSUMPTIONS!B31 -> 0.22
A12: UBS net income | G12: ='UBS STANDALONE'!B4 -> 7200 | H12: ='UBS STANDALONE'!B5 -> 7500 | I12: ='UBS STANDALONE'!B6 -> 7800
A13: CBK net income | G13: ='CBK STANDALONE'!B5 -> 2836 | H13: ='CBK STANDALONE'!B6 -> 2922 | I13: ='CBK STANDALONE'!B7 -> 3009
A14: Synergies | G14: =B8/B9*ASSUMPTIONS!B36 -> 900 | H14: =B8/B9*85% -> 1275 | I14: =B8/B9*100% -> 1500
A15: Less:Restructuring cost | G15: =B8/3 -> 750 | H15: =B8/3 -> 750 | I15: =B8/3 -> 750
A16: Less:Incremental interest | G16: =$E$6*$E$7 -> 103.5 | H16: =$E$6*$E$7 -> 103.5 | I16: =$E$6*$E$7 -> 103.5
A17: Earning before taxes | G17: =G12+G13+G14-G15-G16 -> 10082.5 | H17: =H12+H13+H14-H15-H16 -> 10843.5 | I17: =I12+I13+I14-I15-I16 -> 11455.5
A18: Income tax @22% | G18: =G17*$B$10 -> 2218.15 | H18: =H17*$B$10 -> 2385.57 | I18: =I17*$B$10 -> 2520.21
A19: Proforma combined net income | G19: =G17-G18 -> 7864.35 | H19: =H17-H18 -> 8457.93 | I19: =I17-I18 -> 8935.29
A21: UBS standalone net income | G21: ='UBS STANDALONE'!B4 -> 7200 | H21: ='UBS STANDALONE'!B5 -> 7500 | I21: ='UBS STANDALONE'!B6 -> 7800
A22: UBS standalone shares | G22: 3185 | H22: 3185 | I22: 3185
A23: New shares issued | G23: =$E$5 -> 1212.4547 | H23: =$E$5 -> 1212.4547 | I23: =$E$5 -> 1212.4547
A24: Pro forma shares | G24: =G22+G23 -> 4397.4547 | H24: =H22+H23 -> 4397.4547 | I24: =I22+I23 -> 4397.4547
A26: Pro forma combined EPS | G26: =G19/G24 -> 1.7883868 | H26: =H19/H24 -> 1.9233695 | I26: =I19/I24 -> 2.0319232
A27: UBS standalone EPS | G27: =G12/G22 -> 2.2605965 | H27: =H12/H22 -> 2.3547881 | I27: =I12/I22 -> 2.4489796
A28: Accretion/(dilution)-$ | G28: =G26-G27 -> -0.47220972 | H28: =H26-H27 -> -0.43141862 | I28: =I26-I27 -> -0.41705643
A29: Accretion/(dilution)-% | G29: =G28/G27 -> -0.20888722 | H29: =H28/H27 -> -0.18320911 | I29: =I28/I27 -> -0.17029804
A31: KEY OUTPUTS
A32: Purchase price | B32: =B5 -> 57.458227
A33: Yr 1 Dilution: | B33: =G29 -> -0.20888722
A34: Yr3 Dilution: | B34: =I29 -> -0.17029804
A35: Breakeven: | B35: >2028
